cholespy-2.2.0.dist-info/RECORD
cholespy-2.2.0.dist-info/WHEEL
cholespy-2.2.0.dist-info/METADATA
cholespy-2.2.0.dist-info/licenses/LICENSE
bin/ndmetis
bin/cmpfillin
bin/m2gmetis
bin/mpmetis
bin/graphchk
bin/gpmetis
include/metis.h
cholespy/__init__.py
cholespy/_cholespy_core.cpython-311-darwin.so
lib/libmetis.a
