Metadata-Version: 2.1
Name: cholespy
Version: 2.2.0
Summary: A self-contained sparse Cholesky solver, compatible with CPU and GPU tensor frameworks.
Keywords: sparse,Cholesky,solver,CUDA
Author-Email: Baptiste Nicolet <baptiste.nicolet@epfl.ch>
Classifier: License :: OSI Approved :: BSD License
Project-URL: Homepage, https://github.com/rgl-epfl/cholespy
Requires-Python: >=3.9
